odoo8_addon_website_canonical_url-8.0.1.1.0-py2.7-nspkg.pth
odoo_addons/website_canonical_url/__openerp__.py
odoo_addons/website_canonical_url/__init__.py
odoo_addons/website_canonical_url/README.rst
odoo_addons/website_canonical_url/models/__init__.py
odoo_addons/website_canonical_url/models/website.py
odoo_addons/website_canonical_url/i18n/ru.po
odoo_addons/website_canonical_url/i18n/it.po
odoo_addons/website_canonical_url/i18n/es.po
odoo_addons/website_canonical_url/i18n/ca.po
odoo_addons/website_canonical_url/i18n/sl.po
odoo_addons/website_canonical_url/i18n/de.po
odoo_addons/website_canonical_url/i18n/fr.po
odoo_addons/website_canonical_url/i18n/pt_BR.po
odoo_addons/website_canonical_url/i18n/el_GR.po
odoo_addons/website_canonical_url/i18n/fi.po
odoo_addons/website_canonical_url/i18n/hr_HR.po
odoo_addons/website_canonical_url/views/templates.xml
odoo8_addon_website_canonical_url-8.0.1.1.0.dist-info/top_level.txt
odoo8_addon_website_canonical_url-8.0.1.1.0.dist-info/WHEEL
odoo8_addon_website_canonical_url-8.0.1.1.0.dist-info/RECORD
odoo8_addon_website_canonical_url-8.0.1.1.0.dist-info/metadata.json
odoo8_addon_website_canonical_url-8.0.1.1.0.dist-info/DESCRIPTION.rst
odoo8_addon_website_canonical_url-8.0.1.1.0.dist-info/METADATA
odoo8_addon_website_canonical_url-8.0.1.1.0.dist-info/namespace_packages.txt
